simple_hello_module/__init__.py
simple_hello_module/simple_hello.py
simple_hello_module/extras/__init__.py
simple_hello_module/extras/extra_dash.py
simple_hello_module/extras/extra_text.py
simple_hello_module-0.0.3.dist-info/METADATA
simple_hello_module-0.0.3.dist-info/WHEEL
simple_hello_module-0.0.3.dist-info/top_level.txt
simple_hello_module-0.0.3.dist-info/RECORD
